parakeet_asr/__init__.py
parakeet_asr/cli.py
parakeet_asr/model.py
parakeet_asr/segment.py
parakeet_asr-0.1.0.dist-info/METADATA
parakeet_asr-0.1.0.dist-info/WHEEL
parakeet_asr-0.1.0.dist-info/entry_points.txt
parakeet_asr-0.1.0.dist-info/RECORD
