Metadata-Version: 2.4
Name: parakeet-asr
Version: 0.1.0
Summary: ASR based on NVIDIA parakeet model
Author-email: Daniel Rodriguez <daniel@danielfrg.com>
Requires-Python: ==3.12.*
Requires-Dist: click>=8.2.1
Requires-Dist: nemo-toolkit[asr]>=2.1.0
Requires-Dist: numpy==1.*
